flask_chest/__init__.py
flask_chest/decorator.py
flask_chest/sqlite_utils.py
flask_chest/chests/__init__.py
flask_chest/chests/base.py
flask_chest/chests/custom.py
flask_chest/chests/influxDB.py
flask_chest/chests/sqlite.py
flask_chest/exporter/__init__.py
flask_chest/exporter/base.py
flask_chest/exporter/influxDB.py
flask_chest/exporter/mysql.py
flask_chest-0.0.10.dist-info/METADATA
flask_chest-0.0.10.dist-info/WHEEL
flask_chest-0.0.10.dist-info/top_level.txt
flask_chest-0.0.10.dist-info/RECORD
